[
  {"lt": [{"word": "apsigyventi", "forms": "apsigyvénti, apsigyvena, apsigyveno", "conjugation": "I"}], "en": [{"word": "to move in"}, {"word": "to settle"}], "ru": [{"word": "поселиться"}, {"word": "обосноваться"}], "uk": [{"word": "оселитися"}, {"word": "поселитися"}], "context": "жильё"},
  {"lt": [{"word": "atsiminti", "forms": "atsiminti, atsimena, atsiminė", "conjugation": "I"}], "en": [{"word": "to remember"}, {"word": "to recall"}], "ru": [{"word": "вспомнить"}, {"word": "помнить"}], "uk": [{"word": "пригадати"}, {"word": "пам'ятати"}], "context": "воспоминание"},
  {"lt": [{"word": "atsisveikinti", "forms": "atsisveikinti, atsisveikina, atsisveikino", "conjugation": "I"}], "en": [{"word": "to say goodbye"}, {"word": "to bid farewell"}], "ru": [{"word": "прощаться"}, {"word": "попрощаться"}], "uk": [{"word": "прощатися"}, {"word": "попрощатися"}], "context": "при расставании"},
  {"lt": [{"word": "autis", "forms": "autis, aunasi, avėsi", "conjugation": "Reflexive"}], "en": [{"word": "to put on shoes"}], "ru": [{"word": "надевать обувь"}, {"word": "обуваться"}], "uk": [{"word": "взуватися"}, {"word": "надівати взуття"}], "context": "обувь"},
  {"lt": [{"word": "baigtis", "forms": "baigtis, baigiasi, baigėsi", "conjugation": "Reflexive"}], "en": [{"word": "to end"}, {"word": "to finish"}], "ru": [{"word": "заканчиваться"}, {"word": "закончиться"}], "uk": [{"word": "закінчуватися"}, {"word": "закінчитися"}], "context": "урок, мероприятие"},
  {"lt": [{"word": "čiaudėti", "forms": "čiaudėti, čiaudi, čiaudėjo", "conjugation": "II"}], "en": [{"word": "to sneeze"}], "ru": [{"word": "чихать"}], "uk": [{"word": "чхати"}], "context": "болезнь"},
  {"lt": [{"word": "dažyti", "forms": "dažyti, dažo, dažė", "conjugation": "III"}], "en": [{"word": "to paint"}, {"word": "to dye"}], "ru": [{"word": "красить"}, {"word": "покрасить"}], "uk": [{"word": "фарбувати"}, {"word": "пофарбувати"}], "context": "стены, волосы"},
  {"lt": [{"word": "domėtis", "forms": "domėtis, domisi, domėjosi", "conjugation": "Reflexive II"}], "en": [{"word": "to be interested in"}], "ru": [{"word": "интересоваться"}], "uk": [{"word": "цікавитися"}], "context": "хобби, тема"},
  {"lt": [{"word": "džiovinti", "forms": "džiovinti, džiovina, džiovino", "conjugation": "I"}], "en": [{"word": "to dry"}], "ru": [{"word": "сушить"}, {"word": "высушивать"}], "uk": [{"word": "сушити"}, {"word": "висушувати"}], "context": "бельё, волосы"},
  {"lt": [{"word": "fotografuoti", "forms": "fotografuoti, fotografuoja, fotografavo", "conjugation": "I"}], "en": [{"word": "to photograph"}, {"word": "to take photos"}], "ru": [{"word": "фотографировать"}], "uk": [{"word": "фотографувати"}], "context": "хобби"},
  {"lt": [{"word": "gydyti", "forms": "gydyti, gydo, gydė", "conjugation": "III"}], "en": [{"word": "to treat"}, {"word": "to heal"}], "ru": [{"word": "лечить"}], "uk": [{"word": "лікувати"}], "context": "болезнь"},
  {"lt": [{"word": "jodinėti", "forms": "jodinėti, jodinėja, jodinėjo", "conjugation": "I"}], "en": [{"word": "to ride (a horse)"}], "ru": [{"word": "кататься (на лошади)"}], "uk": [{"word": "їздити верхи"}], "context": "хобби"},
  {"lt": [{"word": "keltis", "forms": "keltis, keliasi, kėlėsi", "conjugation": "Reflexive I"}], "en": [{"word": "to get up"}, {"word": "to rise"}], "ru": [{"word": "вставать"}, {"word": "подниматься"}], "uk": [{"word": "вставати"}, {"word": "підніматися"}], "context": "утром"},
  {"lt": [{"word": "klijuoti", "forms": "klijuoti, klijuoja, klijavo", "conjugation": "I"}], "en": [{"word": "to glue"}, {"word": "to paste"}], "ru": [{"word": "клеить"}, {"word": "приклеивать"}], "uk": [{"word": "клеїти"}, {"word": "приклеювати"}], "context": "поделки, ремонт"},
  {"lt": [{"word": "kolekcionuoti", "forms": "kolekcionuoti, kolekcionuoja, kolekcionavo", "conjugation": "I"}], "en": [{"word": "to collect"}], "ru": [{"word": "коллекционировать"}], "uk": [{"word": "колекціонувати"}], "context": "хобби"},
  {"lt": [{"word": "kosėti", "forms": "kosėti, kosi, kosėjo", "conjugation": "II"}], "en": [{"word": "to cough"}], "ru": [{"word": "кашлять"}], "uk": [{"word": "кашляти"}], "context": "болезнь"},
  {"lt": [{"word": "kviesti", "forms": "kviesti, kviečia, kvietė", "conjugation": "I"}], "en": [{"word": "to invite"}], "ru": [{"word": "приглашать"}, {"word": "пригласить"}], "uk": [{"word": "запрошувати"}, {"word": "запросити"}], "context": "в гости, на мероприятие"},
  {"lt": [{"word": "laimėti", "forms": "laimėti, laimi, laimėjo", "conjugation": "II"}], "en": [{"word": "to win"}], "ru": [{"word": "победить"}, {"word": "выиграть"}], "uk": [{"word": "перемогти"}, {"word": "виграти"}], "context": "соревнование"},
  {"lt": [{"word": "lipdyti", "forms": "lipdyti, lipdo, lipdė", "conjugation": "III"}], "en": [{"word": "to sculpt"}, {"word": "to mould"}], "ru": [{"word": "лепить"}], "uk": [{"word": "ліпити"}], "context": "пластилин, глина"},
  {"lt": [{"word": "lyginti", "forms": "lyginti, lygina, lygino", "conjugation": "I"}], "en": [{"word": "to iron"}, {"word": "to smooth"}], "ru": [{"word": "гладить (одежду)"}, {"word": "утюжить"}], "uk": [{"word": "прасувати"}, {"word": "гладити"}], "context": "бельё"},
  {"lt": [{"word": "maudytis", "forms": "maudytis, maudosi, maudėsi", "conjugation": "Reflexive III"}], "en": [{"word": "to bathe"}, {"word": "to swim"}], "ru": [{"word": "купаться"}], "uk": [{"word": "купатися"}], "context": "ванна, бассейн, море"},
  {"lt": [{"word": "mėgti", "forms": "mėgti, mėgsta, mėgo", "conjugation": "I"}], "en": [{"word": "to like"}, {"word": "to be fond of"}], "ru": [{"word": "любить"}, {"word": "нравиться"}], "uk": [{"word": "любити"}, {"word": "подобатися"}], "context": "хобби, вкусы"},
  {"lt": [{"word": "megzti", "forms": "megzti, mezga, mezgė", "conjugation": "I"}], "en": [{"word": "to knit"}], "ru": [{"word": "вязать"}], "uk": [{"word": "в'язати"}], "context": "хобби"},
  {"lt": [{"word": "mirti", "forms": "mirti, miršta, mirė", "conjugation": "I"}], "en": [{"word": "to die"}], "ru": [{"word": "умирать"}, {"word": "умереть"}], "uk": [{"word": "вмирати"}, {"word": "померти"}], "context": "смерть"},
  {"lt": [{"word": "nardyti", "forms": "nardyti, nardo, nardė", "conjugation": "III"}], "en": [{"word": "to dive"}, {"word": "to scuba dive"}], "ru": [{"word": "нырять"}, {"word": "дайвить"}], "uk": [{"word": "нирнути"}, {"word": "пірнати"}], "context": "хобби, водный спорт"},
  {"lt": [{"word": "nešti", "forms": "nešti, neša, nešė", "conjugation": "I"}], "en": [{"word": "to carry"}, {"word": "to bring"}], "ru": [{"word": "нести"}, {"word": "носить"}], "uk": [{"word": "нести"}, {"word": "носити"}], "context": "груз, вещи"},
  {"lt": [{"word": "pabusti", "forms": "pabusti, pabunda, pabudo", "conjugation": "I"}], "en": [{"word": "to wake up"}], "ru": [{"word": "просыпаться"}, {"word": "проснуться"}], "uk": [{"word": "прокидатися"}, {"word": "прокинутися"}], "context": "утром"},
  {"lt": [{"word": "pailsėti", "forms": "pailsėti, pailsi, pailsėjo", "conjugation": "II"}], "en": [{"word": "to rest"}, {"word": "to relax"}], "ru": [{"word": "отдохнуть"}, {"word": "передохнуть"}], "uk": [{"word": "відпочити"}, {"word": "перепочити"}], "context": "после работы, на каникулах"},
  {"lt": [{"word": "pamiršti", "forms": "pamiršti, pamiršta, pamiršo", "conjugation": "I"}], "en": [{"word": "to forget"}], "ru": [{"word": "забыть"}, {"word": "забывать"}], "uk": [{"word": "забути"}, {"word": "забувати"}], "context": "информация, вещи"},
  {"lt": [{"word": "pasirašyti", "forms": "pasirašyti, pasirašo, pasirašė", "conjugation": "III"}], "en": [{"word": "to sign"}], "ru": [{"word": "подписывать"}, {"word": "подписать"}], "uk": [{"word": "підписувати"}, {"word": "підписати"}], "context": "документ"},
  {"lt": [{"word": "pasivaikščioti", "forms": "pasivaikščioti, pasivaikščioja, pasivaikščiojo", "conjugation": "I"}], "en": [{"word": "to take a walk"}, {"word": "to stroll"}], "ru": [{"word": "погулять"}, {"word": "прогуляться"}], "uk": [{"word": "погуляти"}, {"word": "прогулятися"}], "context": "парк, улица"},
  {"lt": [{"word": "piešti", "forms": "piešti, piešia, piešė", "conjugation": "I"}], "en": [{"word": "to draw"}], "ru": [{"word": "рисовать"}], "uk": [{"word": "малювати"}], "context": "хобби"},
  {"lt": [{"word": "plaukti", "forms": "plaukti, plaukia, plaukė", "conjugation": "I"}], "en": [{"word": "to swim"}, {"word": "to sail"}], "ru": [{"word": "плыть"}, {"word": "плавать"}], "uk": [{"word": "плисти"}, {"word": "плавати"}], "context": "вода, бассейн"},
  {"lt": [{"word": "ploti", "forms": "ploti, ploja, plojo", "conjugation": "I"}], "en": [{"word": "to applaud"}, {"word": "to clap"}], "ru": [{"word": "аплодировать"}, {"word": "хлопать"}], "uk": [{"word": "аплодувати"}, {"word": "плескати"}], "context": "концерт, спектакль"},
  {"lt": [{"word": "pralaimėti", "forms": "pralaimėti, pralaimi, pralaimėjo", "conjugation": "II"}], "en": [{"word": "to lose"}], "ru": [{"word": "проиграть"}, {"word": "проигрывать"}], "uk": [{"word": "програти"}, {"word": "програвати"}], "context": "соревнование"},
  {"lt": [{"word": "praustis", "forms": "praustis, prausasi, prausėsi", "conjugation": "Reflexive I"}], "en": [{"word": "to wash oneself"}, {"word": "to freshen up"}], "ru": [{"word": "умываться"}, {"word": "умыться"}], "uk": [{"word": "вмиватися"}, {"word": "умиватися"}], "context": "утренний ритуал"},
  {"lt": [{"word": "pristatyti", "forms": "pristatyti, pristato, pristatė", "conjugation": "III"}], "en": [{"word": "to introduce"}, {"word": "to present"}], "ru": [{"word": "представлять"}, {"word": "представить"}], "uk": [{"word": "представляти"}, {"word": "представити"}], "context": "знакомство"},
  {"lt": [{"word": "ragauti", "forms": "ragauti, ragauja, ragavo", "conjugation": "I"}], "en": [{"word": "to taste"}], "ru": [{"word": "пробовать"}, {"word": "попробовать"}], "uk": [{"word": "куштувати"}, {"word": "скуштувати"}], "context": "еда"},
  {"lt": [{"word": "registruotis", "forms": "registruotis, registruojasi, registravosi", "conjugation": "Reflexive I"}], "en": [{"word": "to register"}, {"word": "to check in"}], "ru": [{"word": "регистрироваться"}, {"word": "зарегистрироваться"}], "uk": [{"word": "реєструватися"}, {"word": "зареєструватися"}], "context": "аэропорт, поликлиника"},
  {"lt": [{"word": "remontuoti", "forms": "remontuoti, remontuoja, remontavo", "conjugation": "I"}], "en": [{"word": "to repair"}, {"word": "to renovate"}], "ru": [{"word": "ремонтировать"}, {"word": "чинить"}], "uk": [{"word": "ремонтувати"}, {"word": "лагодити"}], "context": "квартира, техника"},
  {"lt": [{"word": "rengtis", "forms": "rengtis, rengiasi, rengėsi", "conjugation": "Reflexive I"}], "en": [{"word": "to get dressed"}], "ru": [{"word": "одеваться"}, {"word": "одеться"}], "uk": [{"word": "одягатися"}, {"word": "одягнутися"}], "context": "утром"},
  {"lt": [{"word": "siųsti", "forms": "siųsti, siunčia, siuntė", "conjugation": "I"}], "en": [{"word": "to send"}], "ru": [{"word": "отправлять"}, {"word": "отослать"}], "uk": [{"word": "надсилати"}, {"word": "відправляти"}], "context": "письмо, посылка"},
  {"lt": [{"word": "siūti", "forms": "siūti, siuva, siuvo", "conjugation": "I"}], "en": [{"word": "to sew"}], "ru": [{"word": "шить"}, {"word": "зашивать"}], "uk": [{"word": "шити"}, {"word": "зашивати"}], "context": "хобби, одежда"},
  {"lt": [{"word": "skalbti", "forms": "skalbti, skalbia, skalbė", "conjugation": "I"}], "en": [{"word": "to do laundry"}, {"word": "to wash clothes"}], "ru": [{"word": "стирать"}, {"word": "постирать"}], "uk": [{"word": "прати"}, {"word": "випрати"}], "context": "одежда, бельё"},
  {"lt": [{"word": "slidinėti", "forms": "slidinėti, slidinėja, slidinėjo", "conjugation": "I"}], "en": [{"word": "to ski"}], "ru": [{"word": "кататься на лыжах"}], "uk": [{"word": "кататися на лижах"}], "context": "зимний спорт"},
  {"lt": [{"word": "sportuoti", "forms": "sportuoti, sportuoja, sportavo", "conjugation": "I"}], "en": [{"word": "to do sport"}, {"word": "to exercise"}], "ru": [{"word": "заниматься спортом"}, {"word": "тренироваться"}], "uk": [{"word": "займатися спортом"}, {"word": "тренуватися"}], "context": "активный образ жизни"},
  {"lt": [{"word": "stovyklauti", "forms": "stovyklauti, stovyklauja, stovyklavo", "conjugation": "I"}], "en": [{"word": "to camp"}, {"word": "to go camping"}], "ru": [{"word": "отдыхать в лагере"}, {"word": "ехать в лагерь"}], "uk": [{"word": "відпочивати в таборі"}, {"word": "відпочивати в наметі"}], "context": "лагерь"},
  {"lt": [{"word": "studijuoti", "forms": "studijuoti, studijuoja, studijavo", "conjugation": "I"}], "en": [{"word": "to study"}, {"word": "to be a student"}], "ru": [{"word": "учиться (в вузе)"}, {"word": "изучать"}], "uk": [{"word": "навчатися (у вузі)"}, {"word": "вивчати"}], "context": "университет"},
  {"lt": [{"word": "susipažinti", "forms": "susipažinti, susipažįsta, susipažino", "conjugation": "I"}], "en": [{"word": "to get acquainted"}, {"word": "to meet someone"}], "ru": [{"word": "познакомиться"}, {"word": "знакомиться"}], "uk": [{"word": "познайомитися"}, {"word": "знайомитися"}], "context": "знакомство"},
  {"lt": [{"word": "susirašinėti", "forms": "susirašinėti, susirašinėja, susirašinėjo", "conjugation": "I"}], "en": [{"word": "to correspond"}, {"word": "to exchange messages"}], "ru": [{"word": "переписываться"}], "uk": [{"word": "листуватися"}, {"word": "переписуватися"}], "context": "письма, сообщения"},
  {"lt": [{"word": "švęsti", "forms": "švęsti, švenčia, šventė", "conjugation": "I"}], "en": [{"word": "to celebrate"}], "ru": [{"word": "праздновать"}, {"word": "отмечать"}], "uk": [{"word": "святкувати"}, {"word": "відзначати"}], "context": "праздник, день рождения"},
  {"lt": [{"word": "tikrinti", "forms": "tikrinti, tikrina, tikrino", "conjugation": "I"}], "en": [{"word": "to check"}, {"word": "to verify"}], "ru": [{"word": "проверять"}, {"word": "проверить"}], "uk": [{"word": "перевіряти"}, {"word": "перевірити"}], "context": "билет, документ"},
  {"lt": [{"word": "užrašyti", "forms": "užrašyti, užrašo, užrašė", "conjugation": "III"}], "en": [{"word": "to write down"}, {"word": "to note"}], "ru": [{"word": "записывать"}, {"word": "записать"}], "uk": [{"word": "записувати"}, {"word": "записати"}], "context": "информация, номер"},
  {"lt": [{"word": "užsisakyti", "forms": "užsisakyti, užsisako, užsisakė", "conjugation": "III Reflexive"}], "en": [{"word": "to order"}, {"word": "to book"}], "ru": [{"word": "заказывать"}, {"word": "заказать"}], "uk": [{"word": "замовляти"}, {"word": "замовити"}], "context": "еда, билет"},
  {"lt": [{"word": "užsiregistruoti", "forms": "užsiregistruoti, užsiregistruoja, užsiregistravo", "conjugation": "I Reflexive"}], "en": [{"word": "to register"}, {"word": "to sign up"}], "ru": [{"word": "записаться"}, {"word": "зарегистрироваться"}], "uk": [{"word": "записатися"}, {"word": "зареєструватися"}], "context": "к врачу, на курсы"},
  {"lt": [{"word": "užjausti", "forms": "užjausti, užjaučia, užjautė", "conjugation": "I"}], "en": [{"word": "to sympathize"}, {"word": "to feel sorry for"}], "ru": [{"word": "сочувствовать"}, {"word": "сострадать"}], "uk": [{"word": "співчувати"}, {"word": "жаліти"}], "context": "утешение"},
  {"lt": [{"word": "vaidinti", "forms": "vaidinti, vaidina, vaidino", "conjugation": "I"}], "en": [{"word": "to act"}, {"word": "to perform"}], "ru": [{"word": "играть (роль)"}, {"word": "выступать"}], "uk": [{"word": "грати (роль)"}, {"word": "виступати"}], "context": "театр, спектакль"},
  {"lt": [{"word": "vogti", "forms": "vogti, vagia, vogė", "conjugation": "I"}], "en": [{"word": "to steal"}], "ru": [{"word": "воровать"}, {"word": "красть"}], "uk": [{"word": "красти"}, {"word": "вкрасти"}], "context": "кража"}
]
